environment.py
knobs.py
knobs-2.1.1.dist-info/LICENCE
knobs-2.1.1.dist-info/METADATA
knobs-2.1.1.dist-info/WHEEL
knobs-2.1.1.dist-info/top_level.txt
knobs-2.1.1.dist-info/RECORD
