Metadata-Version: 2.1
Name: knobs
Version: 2.1.1
Summary: Environment variable manager
Home-page: https://github.com/sthysel/knobs
Author: sthysel
Author-email: sthysel@gmail.com
License: GPLv2
Platform: UNKNOWN
Classifier: Development Status :: 4 - Beta
Classifier: Operating System :: Unix
Classifier: Operating System :: POSIX
Classifier: Programming Language :: Python
Classifier: Programming Language :: Python :: 2.7
Classifier: Programming Language :: Python :: 3.6
Classifier: Programming Language :: Python :: Implementation :: CPython
Classifier: Programming Language :: Python :: Implementation :: PyPy
Classifier: Topic :: Utilities
Requires-Dist: click
Requires-Dist: python-dotenv
Requires-Dist: tabulate
